LICENSE
README.md
setup.cfg
setup.py
acq/__init__.py
acq/discovery.py
acq.egg-info/PKG-INFO
acq.egg-info/SOURCES.txt
acq.egg-info/dependency_links.txt
acq.egg-info/top_level.txt
acq.egg-info/zip-safe
acq/django/__init__.py
acq/django/discovery.py
tests/__init__.py
tests/test_discovery.py
tests/test_django.py
tests/test_publishing.py