Metadata-Version: 2.1
Name: acq
Version: 0.1.0
Summary:  automatic acquisition of modules from packages
Home-page: https://git.sr.ht/~monokrome/acq
Author: Bailey "monokrome" Stoner
Author-email: monokrome@monokro.me
Maintainer: Bailey "monokrome" Stoner
Maintainer-email: monokrome@monokro.me
License: BSD 3-Clause License
License-File: LICENSE
